gitmanipulator/__init__.py
gitmanipulator/main.py
gitmanipulator/controllers/__init__.py
gitmanipulator/controllers/base.py
gitmanipulator/controllers/epic.py
gitmanipulator/controllers/project.py
gitmanipulator/core/__init__.py
gitmanipulator/core/exc.py
gitmanipulator/core/version.py
gitmanipulator/ext/__init__.py
gitmanipulator/plugins/__init__.py
gitmanipulator/service/__init__.py
gitmanipulator/service/gitManager.py
gitmanipulator/templates/__init__.py
gitmanipulator/templates/projects.jinja2
gitmanipulator-1.0.2.dist-info/LICENSE.md
gitmanipulator-1.0.2.dist-info/METADATA
gitmanipulator-1.0.2.dist-info/WHEEL
gitmanipulator-1.0.2.dist-info/entry_points.txt
gitmanipulator-1.0.2.dist-info/top_level.txt
gitmanipulator-1.0.2.dist-info/RECORD
