Metadata-Version: 2.1
Name: gitmanipulator
Version: 1.0.2
Summary: manipulate many git project
Home-page: 
Author: Alex
Author-email: 
License: unlicensed
Platform: UNKNOWN
License-File: LICENSE.md
Requires-Dist: cement (==3.0.6)
Requires-Dist: jinja2
Requires-Dist: pyyaml
Requires-Dist: colorlog
Requires-Dist: tinydb (~=4.7.0)
Requires-Dist: GitPython
Requires-Dist: tqdm
